sorna/__init__.py
sorna/auth.py
sorna/compat.py
sorna/config.py
sorna/exceptions.py
sorna/kernel.py
sorna/request.py
sorna/asyncio/__init__.py
sorna/asyncio/kernel.py
sorna/cli/__init__.py
sorna/cli/__main__.py
sorna/cli/pretty.py
sorna/cli/run.py
sorna_client-0.9.8.dist-info/DESCRIPTION.rst
sorna_client-0.9.8.dist-info/METADATA
sorna_client-0.9.8.dist-info/RECORD
sorna_client-0.9.8.dist-info/WHEEL
sorna_client-0.9.8.dist-info/entry_points.txt
sorna_client-0.9.8.dist-info/metadata.json
sorna_client-0.9.8.dist-info/top_level.txt
