Metadata-Version: 2.0
Name: sorna-client
Version: 0.9.8
Summary: Sorna API Client Library
Home-page: https://github.com/lablup/sorna-client
Author: Lablup Inc.
Author-email: joongi@lablup.com
License: LGPLv3
Platform: UNKNOWN
Classifier: Development Status :: 4 - Beta
Classifier: License :: OSI Approved :: GNU Lesser General Public License v3 or later (LGPLv3+)
Classifier: Intended Audience :: Developers
Classifier: Programming Language :: Python
Classifier: Programming Language :: Python :: 3
Classifier: Programming Language :: Python :: 3.5
Classifier: Programming Language :: Python :: 3.6
Classifier: Operating System :: POSIX
Classifier: Operating System :: MacOS :: MacOS X
Classifier: Environment :: No Input/Output (Daemon)
Classifier: Topic :: Scientific/Engineering
Classifier: Topic :: Software Development
Requires-Python: >=3.5
Requires-Dist: ConfigArgParse (>=0.12.0)
Requires-Dist: aiohttp (>=2.2.0)
Requires-Dist: namedlist (>=1.6)
Requires-Dist: python-dateutil (>=2.5)
Requires-Dist: requests (>=2.12)
Requires-Dist: simplejson
Provides-Extra: ci
Requires-Dist: asynctest; extra == 'ci'
Requires-Dist: codecov; extra == 'ci'
Requires-Dist: pytest (>=3.1); extra == 'ci'
Requires-Dist: pytest-asyncio; extra == 'ci'
Requires-Dist: pytest-cov; extra == 'ci'
Requires-Dist: pytest-mock; extra == 'ci'
Requires-Dist: twine; extra == 'ci'
Requires-Dist: wheel; extra == 'ci'
Provides-Extra: dev
Requires-Dist: asynctest; extra == 'dev'
Requires-Dist: codecov; extra == 'dev'
Requires-Dist: pytest (>=3.1); extra == 'dev'
Requires-Dist: pytest-asyncio; extra == 'dev'
Requires-Dist: pytest-cov; extra == 'dev'
Requires-Dist: pytest-mock; extra == 'dev'
Requires-Dist: twine; extra == 'dev'
Requires-Dist: wheel; extra == 'dev'
Provides-Extra: test
Requires-Dist: asynctest; extra == 'test'
Requires-Dist: codecov; extra == 'test'
Requires-Dist: pytest (>=3.1); extra == 'test'
Requires-Dist: pytest-asyncio; extra == 'test'
Requires-Dist: pytest-cov; extra == 'test'
Requires-Dist: pytest-mock; extra == 'test'
